pfmcnninitialization/__init__.py
pfmcnninitialization/filter_initialization_matrix.py
pfmcnninitialization-0.7.dist-info/LICENSE.txt
pfmcnninitialization-0.7.dist-info/METADATA
pfmcnninitialization-0.7.dist-info/WHEEL
pfmcnninitialization-0.7.dist-info/top_level.txt
pfmcnninitialization-0.7.dist-info/RECORD
