Metadata-Version: 2.1
Name: pfmcnninitialization
Version: 0.7
Summary: A module for constructing parameter initialization matrix of convolutional neural network for genomics using PFM matrix information of transcription factors in Jaspar database.
Home-page: UNKNOWN
Author: zxzong
Author-email: 274573863@qq.com
License: UNKNOWN
Platform: UNKNOWN
Classifier: Programming Language :: Python :: 3
Classifier: License :: OSI Approved :: MIT License
Classifier: Operating System :: OS Independent
Requires-Python: >=3.6
Requires-Dist: numpy
Requires-Dist: pandas
Requires-Dist: wget
